hzgt/__init__.py
hzgt/cmdline.py
hzgt/__version/__init__.py
hzgt/__version/version.txt
hzgt/core/CONST.py
hzgt/core/Decorator.py
hzgt/core/__init__.py
hzgt/core/autoconfig.py
hzgt/core/fileop.py
hzgt/core/ipss.py
hzgt/core/log.py
hzgt/core/strop.py
hzgt/core/sysutils.py
hzgt/tools/FTP.py
hzgt/tools/FileServer.py
hzgt/tools/INI.py
hzgt/tools/MQTT.py
hzgt/tools/REGISTER.py
hzgt/tools/SMTP.py
hzgt/tools/__init__.py
hzgt/tools/extensions_map.ini
hzgt/tools/favicon.ico
hzgt/tools/rsa.js
hzgt/tools/SQL/MYSQL.py
hzgt/tools/SQL/SQLITE.py
hzgt/tools/SQL/__init__.py
hzgt/tools/SQL/sqlhistory.py
hzgt/tools/SQL/sqlcore/SQLutil.py
hzgt/tools/SQL/sqlcore/__init__.py
hzgt/tools/SQL/sqlcore/adapter.py
hzgt/tools/SQL/sqlcore/common.py
hzgt/tools/SQL/sqlcore/connpool.py
hzgt/tools/SQL/sqlcore/qbuilder.py
hzgt-2026.1.30.data/data/hzgt/LICENSE
hzgt-2026.1.30.data/data/hzgt/README.md
hzgt-2026.1.30.data/scripts/cmdline.py
hzgt-2026.1.30.dist-info/LICENSE
hzgt-2026.1.30.dist-info/METADATA
hzgt-2026.1.30.dist-info/WHEEL
hzgt-2026.1.30.dist-info/entry_points.txt
hzgt-2026.1.30.dist-info/top_level.txt
hzgt-2026.1.30.dist-info/RECORD
