Metadata-Version: 2.2
Name: hzgt
Version: 2026.1.30
Summary: A toolbox that includes MQTT, MYSQL, FTP encapsulation, and other gadgets
Home-page: https://github.com/HZGT/hzgt
Author: HZGT
Author-email: 2759444274@qq.com
Classifier: Programming Language :: Python :: 3
Classifier: License :: OSI Approved :: MIT License
Classifier: Operating System :: OS Independent
Requires-Python: >=3.8
License-File: LICENSE
Requires-Dist: click
Requires-Dist: tabulate
Requires-Dist: requests
Requires-Dist: tqdm
Requires-Dist: psutil
Requires-Dist: pymysql
Requires-Dist: sqlalchemy
Requires-Dist: paho-mqtt
Requires-Dist: pyftpdlib
Requires-Dist: dotenv
Provides-Extra: mysql
Requires-Dist: cryptography; extra == "mysql"
Dynamic: author
Dynamic: author-email
Dynamic: classifier
Dynamic: description
Dynamic: description-content-type
Dynamic: home-page
Dynamic: provides-extra
Dynamic: requires-dist
Dynamic: requires-python
Dynamic: summary
